base/__init__.py
base/admin.py
base/apps.py
base/static/vendor/animate.css/animate.compat.css
base/static/vendor/animate.css/animate.css
base/static/vendor/animate.css/animate.min.css
base/static/vendor/aos/aos.css
base/static/vendor/aos/aos.js
base/static/vendor/apexcharts/apexcharts.min.js
base/static/vendor/apexcharts/locales/ar.json
base/static/vendor/apexcharts/locales/ca.json
base/static/vendor/apexcharts/locales/cs.json
base/static/vendor/apexcharts/locales/de.json
base/static/vendor/apexcharts/locales/el.json
base/static/vendor/apexcharts/locales/en.json
base/static/vendor/apexcharts/locales/es.json
base/static/vendor/apexcharts/locales/fa.json
base/static/vendor/apexcharts/locales/fi.json
base/static/vendor/apexcharts/locales/fr.json
base/static/vendor/apexcharts/locales/he.json
base/static/vendor/apexcharts/locales/hi.json
base/static/vendor/apexcharts/locales/hr.json
base/static/vendor/apexcharts/locales/hu.json
base/static/vendor/apexcharts/locales/hy.json
base/static/vendor/apexcharts/locales/id.json
base/static/vendor/apexcharts/locales/it.json
base/static/vendor/apexcharts/locales/ja.json
base/static/vendor/apexcharts/locales/ka.json
base/static/vendor/apexcharts/locales/ko.json
base/static/vendor/apexcharts/locales/lt.json
base/static/vendor/apexcharts/locales/nb.json
base/static/vendor/apexcharts/locales/nl.json
base/static/vendor/apexcharts/locales/pl.json
base/static/vendor/apexcharts/locales/pt-br.json
base/static/vendor/apexcharts/locales/pt.json
base/static/vendor/apexcharts/locales/rs.json
base/static/vendor/apexcharts/locales/ru.json
base/static/vendor/apexcharts/locales/se.json
base/static/vendor/apexcharts/locales/sk.json
base/static/vendor/apexcharts/locales/sl.json
base/static/vendor/apexcharts/locales/sq.json
base/static/vendor/apexcharts/locales/th.json
base/static/vendor/apexcharts/locales/tr.json
base/static/vendor/apexcharts/locales/ua.json
base/static/vendor/apexcharts/locales/zh-cn.json
django_base_ds-0.1.1.dist-info/LICENSE
django_base_ds-0.1.1.dist-info/METADATA
django_base_ds-0.1.1.dist-info/WHEEL
django_base_ds-0.1.1.dist-info/top_level.txt
django_base_ds-0.1.1.dist-info/RECORD
